README.md
setup.py
hard/__init__.py
hard/hard.py
hard.egg-info/PKG-INFO
hard.egg-info/SOURCES.txt
hard.egg-info/dependency_links.txt
hard.egg-info/top_level.txt
sample/__init__.py
sample/sample.py
test/__init__.py
test/hard.py