Metadata-Version: 2.1
Name: hard
Version: 0.0.2
Summary: hard variables: they dumping when the set time
Home-page: https://github.com/eaybek/hard
Author: Erdem Aybek
Author-email: eaybek@gmail.com
License: UNKNOWN
Platform: UNKNOWN
Classifier: Programming Language :: Python :: 3
Classifier: License :: OSI Approved :: MIT License
Classifier: Operating System :: POSIX :: Linux
Classifier: Development Status :: 1 - Planning
Requires-Python: >=3.6
